[{"timestamp":1631686207311,"files":[{"filename":"code-build-result/index.js","previous":2093,"size":4796,"diff":2703}]},{"timestamp":1627042550752,"files":[{"filename":"code-build-result/index.js","previous":2115,"size":2093,"diff":-22}]},{"timestamp":1606329576971,"files":[{"filename":"code-build-result/index.js","previous":2109,"size":2115,"diff":6}]},{"timestamp":1596458502454,"files":[{"filename":"code-build-result/index.js","previous":5971,"size":2109,"diff":-3862}]},{"timestamp":1596407696575,"files":[{"filename":"code-build-result/index.js","previous":2346,"size":5971,"diff":3625}]}]
