[{"timestamp":1643739695322,"files":[{"filename":"check-parameter/index.js","previous":2231,"size":2208,"diff":-23}]},{"timestamp":1643739156067,"files":[{"filename":"check-parameter/index.js","previous":2208,"size":2231,"diff":23}]},{"timestamp":1643738715897,"files":[{"filename":"check-parameter/index.js","previous":2231,"size":2208,"diff":-23}]},{"timestamp":1643738518037,"files":[{"filename":"check-parameter/index.js","previous":0,"size":2231,"diff":2231}]},{"timestamp":1643732386339,"files":[{"filename":"check-parameter/index.js","previous":2208,"size":0,"diff":-2208}]},{"timestamp":1631688054589,"files":[{"filename":"check-parameter/index.js","previous":2166,"size":2208,"diff":42}]},{"timestamp":1606329520238,"files":[{"filename":"check-parameter/index.js","previous":2158,"size":2166,"diff":8}]},{"timestamp":1596442979475,"files":[{"filename":"check-parameter/index.js","previous":6031,"size":2158,"diff":-3873}]},{"timestamp":1596407637891,"files":[{"filename":"check-parameter/index.js","previous":2354,"size":6031,"diff":3677}]}]
