[{"timestamp":1631688053756,"files":[{"filename":"merge-branches/index.js","previous":2121,"size":4875,"diff":2754}]},{"timestamp":1606329521052,"files":[{"filename":"merge-branches/index.js","previous":2113,"size":2121,"diff":8}]},{"timestamp":1596468947179,"files":[{"filename":"merge-branches/index.js","previous":2111,"size":2113,"diff":2}]},{"timestamp":1596439804155,"files":[{"filename":"merge-branches/index.js","previous":6009,"size":2111,"diff":-3898}]},{"timestamp":1596407638195,"files":[{"filename":"merge-branches/index.js","previous":2330,"size":6009,"diff":3679}]}]
